setup.py
src/clish/__init__.py
src/clish/interactive.py
src/clish.egg-info/PKG-INFO
src/clish.egg-info/SOURCES.txt
src/clish.egg-info/dependency_links.txt
src/clish.egg-info/top_level.txt