Metadata-Version: 1.1
Name: clish
Version: 0.1
Summary: Command Line Interactive Shell Framework.
Home-page: https://github.com/vit1251/clish
Author: Vitold Sedyshev
Author-email: vit1251@gmail.com
License: BSD
Keywords: cli command line shell framework readline console
Platform: UNKNOWN
Classifier: Development Status :: 3 - Alpha
Classifier: Topic :: Utilities
Classifier: License :: OSI Approved :: BSD License
